Metadata-Version: 2.1
Name: client_chat_pyqt_001
Version: 0.1
Summary: client_chat_pyqt5
Home-page: UNKNOWN
Author: GeekBrains
Author-email: volimots@mail.ru
License: UNKNOWN
Platform: UNKNOWN
